ClipCap-1.0.0.data/data/README.md
clipcap/__init__.py
clipcap/encoders/__init__.py
clipcap/encoders/_baseformat.py
clipcap/encoders/args.py
clipcap/encoders/base.py
clipcap/encoders/clap.py
clipcap/encoders/clip.py
clipcap/eval/__init__.py
clipcap/finetune/__init__.py
clipcap/inference/__init__.py
clipcap/model/__init__.py
clipcap/model/args.py
clipcap/model/attention.py
clipcap/model/config.py
clipcap/model/mapper.py
clipcap/model/model.py
clipcap/preprocess/__init__.py
clipcap/preprocess/__main__.py
clipcap/preprocess/args.py
clipcap/preprocess/distributor.py
clipcap/preprocess/mapper.py
clipcap/preprocess/preprocess.py
clipcap/preprocess/reader.py
clipcap/preprocess/runner.py
clipcap/preprocess/writer.py
clipcap/train/__init__.py
clipcap/train/__main__.py
clipcap/train/args.py
clipcap/train/callback.py
clipcap/train/dataloader.py
clipcap/train/train.py
ClipCap-1.0.0.dist-info/METADATA
ClipCap-1.0.0.dist-info/WHEEL
ClipCap-1.0.0.dist-info/top_level.txt
ClipCap-1.0.0.dist-info/RECORD
