Metadata-Version: 2.1
Name: ClipCap
Version: 1.0.0
Summary: Using pretrained encoder and language models to generate captions from multimedia inputs.
Home-page: https://github.com/TheoCoombes/ClipCap
Author: Theo Coombes
Author-email: theocoombes06@gmail.com
License: MIT
Keywords: machine learning,image captioning,audio captioning,CLIP,GPT
Platform: UNKNOWN
Classifier: Development Status :: 4 - Beta
Classifier: Intended Audience :: Developers
Classifier: Topic :: Scientific/Engineering :: Artificial Intelligence
Classifier: License :: OSI Approved :: MIT License
Classifier: Programming Language :: Python :: 3.6
Requires-Dist: pytorch-lightning
Requires-Dist: embedding-reader
Requires-Dist: transformers
Requires-Dist: fsspec
Requires-Dist: PyYAML
Requires-Dist: torch
Requires-Dist: numpy
